karrio/mappers/dicom/__init__.py
karrio/mappers/dicom/mapper.py
karrio/mappers/dicom/proxy.py
karrio/mappers/dicom/settings.py
karrio/plugins/dicom/__init__.py
karrio/providers/dicom/__init__.py
karrio/providers/dicom/error.py
karrio/providers/dicom/rate.py
karrio/providers/dicom/tracking.py
karrio/providers/dicom/units.py
karrio/providers/dicom/utils.py
karrio/providers/dicom/pickup/__init__.py
karrio/providers/dicom/pickup/cancel.py
karrio/providers/dicom/pickup/create.py
karrio/providers/dicom/pickup/update.py
karrio/providers/dicom/shipment/__init__.py
karrio/providers/dicom/shipment/cancel.py
karrio/providers/dicom/shipment/create.py
karrio/schemas/dicom/__init__.py
karrio/schemas/dicom/pickups.py
karrio/schemas/dicom/rates.py
karrio/schemas/dicom/shipments.py
karrio/schemas/dicom/tracking.py
karrio_dicom-2026.1.4.dist-info/METADATA
karrio_dicom-2026.1.4.dist-info/WHEEL
karrio_dicom-2026.1.4.dist-info/entry_points.txt
karrio_dicom-2026.1.4.dist-info/top_level.txt
karrio_dicom-2026.1.4.dist-info/RECORD
